codeium_jupyter/__init__.py
codeium_jupyter/_version.py
codeium_jupyter-2.1.0.data/data/share/jupyter/labextensions/codeium-jupyter/package.json
codeium_jupyter-2.1.0.data/data/share/jupyter/labextensions/codeium-jupyter/schemas/codeium-jupyter/inline-provider.json
codeium_jupyter-2.1.0.data/data/share/jupyter/labextensions/codeium-jupyter/schemas/codeium-jupyter/package.json.orig
codeium_jupyter-2.1.0.data/data/share/jupyter/labextensions/codeium-jupyter/static/24.759abfaad0d6c6bc7370.js
codeium_jupyter-2.1.0.data/data/share/jupyter/labextensions/codeium-jupyter/static/362.ae000fa5d41ebbf0212b.js
codeium_jupyter-2.1.0.data/data/share/jupyter/labextensions/codeium-jupyter/static/392.668d2f4dfae2e7d89bcf.js
codeium_jupyter-2.1.0.data/data/share/jupyter/labextensions/codeium-jupyter/static/557.19d51cc4e01d3629e103.js
codeium_jupyter-2.1.0.data/data/share/jupyter/labextensions/codeium-jupyter/static/728.d4cdbc79dc360b579239.js
codeium_jupyter-2.1.0.data/data/share/jupyter/labextensions/codeium-jupyter/static/960.b4fb76398f30e1583e0f.js
codeium_jupyter-2.1.0.data/data/share/jupyter/labextensions/codeium-jupyter/static/967.03b7775256a1702fea95.js
codeium_jupyter-2.1.0.data/data/share/jupyter/labextensions/codeium-jupyter/static/remoteEntry.e4d3b6769d60444902c3.js
codeium_jupyter-2.1.0.data/data/share/jupyter/labextensions/codeium-jupyter/static/style.js
codeium_jupyter-2.1.0.data/data/share/jupyter/labextensions/codeium-jupyter/static/third-party-licenses.json
codeium_jupyter-2.1.0.data/data/share/jupyter/labextensions/codeium-jupyter/install.json
codeium_jupyter-2.1.0.dist-info/METADATA
codeium_jupyter-2.1.0.dist-info/WHEEL
codeium_jupyter-2.1.0.dist-info/licenses/LICENSE
codeium_jupyter-2.1.0.dist-info/RECORD
