Metadata-Version: 2.3
Name: codeium-jupyter
Version: 2.1.0
Dynamic: Keywords
Summary: The modern coding superpower: free AI code acceleration plugin for your favorite languages. Type less. Code more. Ship faster.
Project-URL: Homepage, https://github.com/Exafunction/codeium.jupyter
Project-URL: Bug Tracker, https://discord.gg/3XFf78nAx5
Project-URL: Repository, https://github.com/Exafunction/codeium.jupyter.git
Author: Exafunction Inc.
License: BSD 3-Clause License
License-File: LICENSE
Classifier: Framework :: Jupyter
Classifier: Framework :: Jupyter :: JupyterLab
Classifier: Framework :: Jupyter :: JupyterLab :: 4
Classifier: Framework :: Jupyter :: JupyterLab :: Extensions
Classifier: Framework :: Jupyter :: JupyterLab :: Extensions :: Prebuilt
Classifier: License :: OSI Approved :: BSD License
Classifier: Programming Language :: Python
Classifier: Programming Language :: Python :: 3
Classifier: Programming Language :: Python :: 3.8
Classifier: Programming Language :: Python :: 3.9
Classifier: Programming Language :: Python :: 3.10
Classifier: Programming Language :: Python :: 3.11
Classifier: Programming Language :: Python :: 3.12
Requires-Python: >=3.8
